[
    {
      "actor_id": 18918,
      "model": "movies.actor",
      "fields": {
        "name": "Dwayne Johnson",
        "profile_path": "https://image.tmdb.org/t/p/original/cgoy7t5Ve075naBPcewZrc08qGw.jpg"
      }
    },
    {
      "actor_id": 83860,
      "model": "movies.actor",
      "fields": {
        "name": "Aldis Hodge",
        "profile_path": "https://image.tmdb.org/t/p/original/jPpnaAGFXaIeOrRNUHIHxk3fIJL.jpg"
      }
    },
    {
      "actor_id": 1253353,
      "model": "movies.actor",
      "fields": {
        "name": "Noah Centineo",
        "profile_path": "https://image.tmdb.org/t/p/original/p1bcst401RyxfDGykx2iQLI7CV5.jpg"
      }
    },
    {
      "actor_id": 164945,
      "model": "movies.actor",
      "fields": {
        "name": "Sarah Shahi",
        "profile_path": "https://image.tmdb.org/t/p/original/shiLCJNyvi9xlUZw4bTuRkhrKpm.jpg"
      }
    },
    {
      "actor_id": 2042690,
      "model": "movies.actor",
      "fields": {
        "name": "Quintessa Swindell",
        "profile_path": "https://image.tmdb.org/t/p/original/xKUFfFJR6o5Ka7AmetGMYjSmBGO.jpg"
      }
    },
    {
      "actor_id": 1396124,
      "model": "movies.actor",
      "fields": {
        "name": "Sosie Bacon",
        "profile_path": "https://image.tmdb.org/t/p/original/hMsjirweIK9wGuy49l52b8SnLuv.jpg"
      }
    },
    {
      "actor_id": 59219,
      "model": "movies.actor",
      "fields": {
        "name": "Kyle Gallner",
        "profile_path": "https://image.tmdb.org/t/p/original/v7wfYXfakHyeNudiATORtlQ6mny.jpg"
      }
    },
    {
      "actor_id": 145245,
      "model": "movies.actor",
      "fields": {
        "name": "Caitlin Stasey",
        "profile_path": "https://image.tmdb.org/t/p/original/8Cxs1enzkEsvIlfBaiuadsNTX8J.jpg"
      }
    },
    {
      "actor_id": 198847,
      "model": "movies.actor",
      "fields": {
        "name": "Jessie T. Usher",
        "profile_path": "https://image.tmdb.org/t/p/original/iiu9dkYEkHJPMf7TzbrhhgwRvlt.jpg"
      }
    },
    {
      "actor_id": 53493,
      "model": "movies.actor",
      "fields": {
        "name": "Kal Penn",
        "profile_path": "https://image.tmdb.org/t/p/original/yICM1JcxKbEpaqTUreY0yFMIc8W.jpg"
      }
    },
    {
      "actor_id": 1083010,
      "model": "movies.actor",
      "fields": {
        "name": "Letitia Wright",
        "profile_path": "https://image.tmdb.org/t/p/original/kfA5KhyU6OSy4NrMzHCxYU7A0DW.jpg"
      }
    },
    {
      "actor_id": 1267329,
      "model": "movies.actor",
      "fields": {
        "name": "Lupita Nyong'o",
        "profile_path": "https://image.tmdb.org/t/p/original/mJMpsADPpt0bmXEzs3ywrUiCkpD.jpg"
      }
    },
    {
      "actor_id": 82104,
      "model": "movies.actor",
      "fields": {
        "name": "Danai Gurira",
        "profile_path": "https://image.tmdb.org/t/p/original/bCjz32aVpyufnPjzLPOtV5DEXKK.jpg"
      }
    },
    {
      "actor_id": 1447932,
      "model": "movies.actor",
      "fields": {
        "name": "Winston Duke",
        "profile_path": "https://image.tmdb.org/t/p/original/MhBiZbryibwuoEtPL9Ns8pYHC1.jpg"
      }
    },
    {
      "actor_id": 2133996,
      "model": "movies.actor",
      "fields": {
        "name": "Dominique Thorne",
        "profile_path": "https://image.tmdb.org/t/p/original/tuLlp79SfYc4mLzzjdC2ekLI7qd.jpg"
      }
    },
    {
      "actor_id": 3258776,
      "model": "movies.actor",
      "fields": {
        "name": "Pavlo Aldoshyn",
        "profile_path": "https://image.tmdb.org/t/p/original/Vi4YZuPX6oFVNeaugZ8YalOFSg.jpg"
      }
    },
    {
      "actor_id": 2232024,
      "model": "movies.actor",
      "fields": {
        "name": "Maryna Koshkina",
        "profile_path": "https://image.tmdb.org/t/p/original/eLPvR0xFkOOKtVjL7UWD6sFs5dF.jpg"
      }
    },
    {
      "actor_id": 2039497,
      "model": "movies.actor",
      "fields": {
        "name": "Andrei Mostrenko",
        "profile_path": "https://image.tmdb.org/t/p/original/ovCSFuWwBqgb42uPOxxbIaKttce.jpg"
      }
    },
    {
      "actor_id": 1916805,
      "model": "movies.actor",
      "fields": {
        "name": "Roman Semysal",
        "profile_path": "https://image.tmdb.org/t/p/originalNone"
      }
    },
    {
      "actor_id": 2342168,
      "model": "movies.actor",
      "fields": {
        "name": "Roman Yasinovskyi",
        "profile_path": "https://image.tmdb.org/t/p/original/oNGKZ1TJypBbXQjUmSC7ycOU4PF.jpg"
      }
    },
    {
      "actor_id": 1882502,
      "model": "movies.actor",
      "fields": {
        "name": "Lauren LaVera",
        "profile_path": "https://image.tmdb.org/t/p/original/wrVoBR5YhdEcadqwPICkcXXTbWk.jpg"
      }
    },
    {
      "actor_id": 1880016,
      "model": "movies.actor",
      "fields": {
        "name": "David Howard Thornton",
        "profile_path": "https://image.tmdb.org/t/p/original/9nYijs4ACzjg93zKezLiLmuRGvp.jpg"
      }
    },
    {
      "actor_id": 2787720,
      "model": "movies.actor",
      "fields": {
        "name": "Elliott Fullam",
        "profile_path": "https://image.tmdb.org/t/p/original/dNsFLihmWfA2KCENbZCtq9AjSob.jpg"
      }
    },
    {
      "actor_id": 3383606,
      "model": "movies.actor",
      "fields": {
        "name": "Sarah Voigt",
        "profile_path": "https://image.tmdb.org/t/p/originalNone"
      }
    },
    {
      "actor_id": 3678959,
      "model": "movies.actor",
      "fields": {
        "name": "Kailey Hyman",
        "profile_path": "https://image.tmdb.org/t/p/originalNone"
      }
    },
    {
      "actor_id": 1164823,
      "model": "movies.actor",
      "fields": {
        "name": "Óscar Barberán",
        "profile_path": "https://image.tmdb.org/t/p/original/3Knf7YGrqS8sfXNPo7k15TIJe92.jpg"
      }
    },
    {
      "actor_id": 1021607,
      "model": "movies.actor",
      "fields": {
        "name": "Luis Posada",
        "profile_path": "https://image.tmdb.org/t/p/original/tTqHaQkpTbUDg4hPBHRoR4cJiFN.jpg"
      }
    },
    {
      "actor_id": 114463,
      "model": "movies.actor",
      "fields": {
        "name": "Michelle Jenner",
        "profile_path": "https://image.tmdb.org/t/p/original/g3JyHqwBcV7g1ds3dHtWkDXyXqb.jpg"
      }
    },
    {
      "actor_id": 3641083,
      "model": "movies.actor",
      "fields": {
        "name": "Anuska Alborg",
        "profile_path": "https://image.tmdb.org/t/p/originalNone"
      }
    },
    {
      "actor_id": 114460,
      "model": "movies.actor",
      "fields": {
        "name": "Alexandra Jiménez",
        "profile_path": "https://image.tmdb.org/t/p/original/wkVjpWajYRV1Bj7OyJmmFcb5ixF.jpg"
      }
    },
    {
      "actor_id": 1356210,
      "model": "movies.actor",
      "fields": {
        "name": "Millie Bobby Brown",
        "profile_path": "https://image.tmdb.org/t/p/original/2685xGmq68G6tmnUbfgSR6rywEV.jpg"
      }
    },
    {
      "actor_id": 73968,
      "model": "movies.actor",
      "fields": {
        "name": "Henry Cavill",
        "profile_path": "https://image.tmdb.org/t/p/original/iWdKjMry5Pt7vmxU7bmOQsIUyHa.jpg"
      }
    },
    {
      "actor_id": 1558986,
      "model": "movies.actor",
      "fields": {
        "name": "Louis Partridge",
        "profile_path": "https://image.tmdb.org/t/p/original/wuZNRskGHWWLo3uS22VcgKcJgZB.jpg"
      }
    },
    {
      "actor_id": 1283,
      "model": "movies.actor",
      "fields": {
        "name": "Helena Bonham Carter",
        "profile_path": "https://image.tmdb.org/t/p/original/DDeITcCpnBd0CkAIRPhggy9bt5.jpg"
      }
    },
    {
      "actor_id": 11207,
      "model": "movies.actor",
      "fields": {
        "name": "David Thewlis",
        "profile_path": "https://image.tmdb.org/t/p/original/sNuYyT8ocLlQr3TdAW9CoKVbCU8.jpg"
      }
    },
    {
      "actor_id": 11107,
      "model": "movies.actor",
      "fields": {
        "name": "Ben Foster",
        "profile_path": "https://image.tmdb.org/t/p/original/4le1PMWTGp7y2IBmZEIOHfE3HAB.jpg"
      }
    },
    {
      "actor_id": 103994,
      "model": "movies.actor",
      "fields": {
        "name": "Sophie Lowe",
        "profile_path": "https://image.tmdb.org/t/p/original/5nco3uflgKK5JGmoLbc0Yna34ZQ.jpg"
      }
    },
    {
      "actor_id": 3895,
      "model": "movies.actor",
      "fields": {
        "name": "Michael Caine",
        "profile_path": "https://image.tmdb.org/t/p/original/hZruclwEPCKw3e83rnFSIH5sRFZ.jpg"
      }
    },
    {
      "actor_id": 1844,
      "model": "movies.actor",
      "fields": {
        "name": "Til Schweiger",
        "profile_path": "https://image.tmdb.org/t/p/original/oBoY5DNa2DmAxixjmJFXgjA2z7A.jpg"
      }
    },
    {
      "actor_id": 1247,
      "model": "movies.actor",
      "fields": {
        "name": "Matthew Goode",
        "profile_path": "https://image.tmdb.org/t/p/original/3XaKKl0bKswTWbJ0Lh9nZ4UdAQo.jpg"
      }
    },
    {
      "actor_id": 1310902,
      "model": "movies.actor",
      "fields": {
        "name": "Bárbara de Regil",
        "profile_path": "https://image.tmdb.org/t/p/original/70TU7lNXo7AOY1zpe44OPpWb0it.jpg"
      }
    },
    {
      "actor_id": 2177750,
      "model": "movies.actor",
      "fields": {
        "name": "Iñaki Godoy",
        "profile_path": "https://image.tmdb.org/t/p/original/cjgF30gIyrHMzEk2dvilmRanDAL.jpg"
      }
    },
    {
      "actor_id": 1240118,
      "model": "movies.actor",
      "fields": {
        "name": "Sara Maldonado",
        "profile_path": "https://image.tmdb.org/t/p/original/4WqPvFBFkPOP6TMVNW00wInEVCA.jpg"
      }
    },
    {
      "actor_id": 3468540,
      "model": "movies.actor",
      "fields": {
        "name": "Vincent Michael Webb",
        "profile_path": "https://image.tmdb.org/t/p/originalNone"
      }
    },
    {
      "actor_id": 2385744,
      "model": "movies.actor",
      "fields": {
        "name": "Mayra Batalla",
        "profile_path": "https://image.tmdb.org/t/p/original/geLzEUg9FDLQr4C2UoipPvmRKS1.jpg"
      }
    },
    {
      "actor_id": 119592,
      "model": "movies.actor",
      "fields": {
        "name": "Aubrey Plaza",
        "profile_path": "https://image.tmdb.org/t/p/original/4pPvrQmrzQCYpgLo8WM1AW8myoe.jpg"
      }
    },
    {
      "actor_id": 51995,
      "model": "movies.actor",
      "fields": {
        "name": "Theo Rossi",
        "profile_path": "https://image.tmdb.org/t/p/original/344QE41Jileu4OE41cmYgBxc5BF.jpg"
      }
    },
    {
      "actor_id": 25382,
      "model": "movies.actor",
      "fields": {
        "name": "Megalyn Echikunwoke",
        "profile_path": "https://image.tmdb.org/t/p/original/6MlcgFphohSBTvOTDMEQwQzs66A.jpg"
      }
    },
    {
      "actor_id": 11150,
      "model": "movies.actor",
      "fields": {
        "name": "Gina Gershon",
        "profile_path": "https://image.tmdb.org/t/p/original/khuZCNBmgNJ5jC4ejCkcsc8k79p.jpg"
      }
    },
    {
      "actor_id": 1807178,
      "model": "movies.actor",
      "fields": {
        "name": "Jonathan Avigdori",
        "profile_path": "https://image.tmdb.org/t/p/original/7TBQdiIPB0Kkjuc4l7Xdw9O5D3p.jpg"
      }
    },
    {
      "actor_id": 2461,
      "model": "movies.actor",
      "fields": {
        "name": "Mel Gibson",
        "profile_path": "https://image.tmdb.org/t/p/original/oSOYCghY3XcXBYqMA0fsEi8WKaa.jpg"
      }
    },
    {
      "actor_id": 6863,
      "model": "movies.actor",
      "fields": {
        "name": "Kevin Dillon",
        "profile_path": "https://image.tmdb.org/t/p/original/tIadFMFzA6LcXaAaVpJmrd7waXQ.jpg"
      }
    },
    {
      "actor_id": 5528,
      "model": "movies.actor",
      "fields": {
        "name": "William Moseley",
        "profile_path": "https://image.tmdb.org/t/p/original/wPahfIdOR6ohIgmgVrCb3RPApAU.jpg"
      }
    },
    {
      "actor_id": 19197,
      "model": "movies.actor",
      "fields": {
        "name": "John Robinson",
        "profile_path": "https://image.tmdb.org/t/p/original/prehpEqJzLvsGHzu7gbhFsDSo1J.jpg"
      }
    },
    {
      "actor_id": 34627,
      "model": "movies.actor",
      "fields": {
        "name": "Nadia Farès",
        "profile_path": "https://image.tmdb.org/t/p/original/uvomxwk2CfO8scOsR60CxHGM2J3.jpg"
      }
    },
    {
      "actor_id": 1817397,
      "model": "movies.actor",
      "fields": {
        "name": "Sydney Craven",
        "profile_path": "https://image.tmdb.org/t/p/original/zt0pdMqP5VfJc7Fp2ijh4Evxe0m.jpg"
      }
    },
    {
      "actor_id": 2738561,
      "model": "movies.actor",
      "fields": {
        "name": "Imran Adams",
        "profile_path": "https://image.tmdb.org/t/p/original/rMur2CMkMWndIfP4k6c1Jt1wXLU.jpg"
      }
    },
    {
      "actor_id": 3425159,
      "model": "movies.actor",
      "fields": {
        "name": "Jarreau Benjamin",
        "profile_path": "https://image.tmdb.org/t/p/original/jugGpoY0ecVwCSN0V2vGWQcGvWU.jpg"
      }
    },
    {
      "actor_id": 3326872,
      "model": "movies.actor",
      "fields": {
        "name": "Matt Barkley",
        "profile_path": "https://image.tmdb.org/t/p/original/k1xY3jyYCf24NItpLSnrT01AjgU.jpg"
      }
    },
    {
      "actor_id": 1070855,
      "model": "movies.actor",
      "fields": {
        "name": "Peter Brooke",
        "profile_path": "https://image.tmdb.org/t/p/original/5fRrmo1Xi9IkiVyypMgOPgZq5ed.jpg"
      }
    },
    {
      "actor_id": 220692,
      "model": "movies.actor",
      "fields": {
        "name": "Alban Lenoir",
        "profile_path": "https://image.tmdb.org/t/p/original/jOWPgqzpvsaxzgBNzDqs2RR5jI6.jpg"
      }
    },
    {
      "actor_id": 1145003,
      "model": "movies.actor",
      "fields": {
        "name": "Stéfi Celma",
        "profile_path": "https://image.tmdb.org/t/p/original/kyB5o93J4vhPLriy1NrSDuxY9IP.jpg"
      }
    },
    {
      "actor_id": 83966,
      "model": "movies.actor",
      "fields": {
        "name": "Pascale Arbillot",
        "profile_path": "https://image.tmdb.org/t/p/original/sFLTfpEqhkEYwYKWxrWlGW2CVXt.jpg"
      }
    },
    {
      "actor_id": 221633,
      "model": "movies.actor",
      "fields": {
        "name": "Sébastien Lalanne",
        "profile_path": "https://image.tmdb.org/t/p/original/28oNL7uSHSJiaDnHWqnx56E1cvW.jpg"
      }
    },
    {
      "actor_id": 126771,
      "model": "movies.actor",
      "fields": {
        "name": "Diego Martín",
        "profile_path": "https://image.tmdb.org/t/p/original/vLCrfjWAS6cjN3CUE7p3HYPYoev.jpg"
      }
    },
    {
      "actor_id": 54633,
      "model": "movies.actor",
      "fields": {
        "name": "Grace Caroline Currey",
        "profile_path": "https://image.tmdb.org/t/p/original/fhwQWWTwl8r613puGYKMyf9H8mQ.jpg"
      }
    },
    {
      "actor_id": 1279279,
      "model": "movies.actor",
      "fields": {
        "name": "Virginia Gardner",
        "profile_path": "https://image.tmdb.org/t/p/original/1DnNysK267b0te48KCkUlTKoTzj.jpg"
      }
    },
    {
      "actor_id": 47296,
      "model": "movies.actor",
      "fields": {
        "name": "Jeffrey Dean Morgan",
        "profile_path": "https://image.tmdb.org/t/p/original/m8bdrmh6ExDCGQ64E83mHg002YV.jpg"
      }
    },
    {
      "actor_id": 2174509,
      "model": "movies.actor",
      "fields": {
        "name": "Mason Gooding",
        "profile_path": "https://image.tmdb.org/t/p/original/bmlry1xqBzNgv8Chm783ss93Cvg.jpg"
      }
    },
    {
      "actor_id": 945542,
      "model": "movies.actor",
      "fields": {
        "name": "Jasper Cole",
        "profile_path": "https://image.tmdb.org/t/p/original/18mmNj8eKPn9a1n3G0yvy650Bd8.jpg"
      }
    },
    {
      "actor_id": 3631223,
      "model": "movies.actor",
      "fields": {
        "name": "Felix Kammerer",
        "profile_path": "https://image.tmdb.org/t/p/original/5BaOoPpTaYavo4mnmuPU1CffuwX.jpg"
      }
    },
    {
      "actor_id": 1111158,
      "model": "movies.actor",
      "fields": {
        "name": "Albrecht Schuch",
        "profile_path": "https://image.tmdb.org/t/p/original/bYqsnHVbaLTnffo4Dj5UiyPBm4U.jpg"
      }
    },
    {
      "actor_id": 1820948,
      "model": "movies.actor",
      "fields": {
        "name": "Aaron Hilmer",
        "profile_path": "https://image.tmdb.org/t/p/original/vrckcaBmTCHQAXQOwKSa2tYZMBd.jpg"
      }
    },
    {
      "actor_id": 212930,
      "model": "movies.actor",
      "fields": {
        "name": "Edin Hasanović",
        "profile_path": "https://image.tmdb.org/t/p/original/MW0VhzAHi3oMtnzNuESbpx02Wa.jpg"
      }
    },
    {
      "actor_id": 6086,
      "model": "movies.actor",
      "fields": {
        "name": "Devid Striesow",
        "profile_path": "https://image.tmdb.org/t/p/original/dV5Sdfa7ED8gkbof8pWuBfPR7lo.jpg"
      }
    },
    {
      "actor_id": 1066986,
      "model": "movies.actor",
      "fields": {
        "name": "Zlatan Ibrahimović",
        "profile_path": "https://image.tmdb.org/t/p/original/pn26udmWYWTm6iIYuUCVyHuVtIT.jpg"
      }
    },
    {
      "actor_id": 2087866,
      "model": "movies.actor",
      "fields": {
        "name": "Megan Rapinoe",
        "profile_path": "https://image.tmdb.org/t/p/original/nzGh8aH3jiaU9akABm93SBup2tY.jpg"
      }
    },
    {
      "actor_id": 71041,
      "model": "movies.actor",
      "fields": {
        "name": "'Weird Al' Yankovic",
        "profile_path": "https://image.tmdb.org/t/p/original/1MjdjnXHokywKz6LZ1b26O5FklA.jpg"
      }
    },
    {
      "actor_id": 3792864,
      "model": "movies.actor",
      "fields": {
        "name": "Rob Stone",
        "profile_path": "https://image.tmdb.org/t/p/original/mEihko8LwfdFokoLH7uN9LRssa7.jpg"
      }
    },
    {
      "actor_id": 2563800,
      "model": "movies.actor",
      "fields": {
        "name": "Kieran Walton",
        "profile_path": "https://image.tmdb.org/t/p/originalNone"
      }
    },
    {
      "actor_id": 77517,
      "model": "movies.actor",
      "fields": {
        "name": "Isabelle Fuhrman",
        "profile_path": "https://image.tmdb.org/t/p/original/borthNRiTGa7oKZjLKHuUGUrZdq.jpg"
      }
    },
    {
      "actor_id": 12041,
      "model": "movies.actor",
      "fields": {
        "name": "Julia Stiles",
        "profile_path": "https://image.tmdb.org/t/p/original/9PJ6G5begxnZkkwvqZqMs0Iwn5o.jpg"
      }
    },
    {
      "actor_id": 58014,
      "model": "movies.actor",
      "fields": {
        "name": "Rossif Sutherland",
        "profile_path": "https://image.tmdb.org/t/p/original/25N7FFIGuPxSTCMqe0vrywzPwnv.jpg"
      }
    },
    {
      "actor_id": 2563029,
      "model": "movies.actor",
      "fields": {
        "name": "Matthew Finlan",
        "profile_path": "https://image.tmdb.org/t/p/original/eAyxxChemfnTDcWOFNDXxr5Zeh8.jpg"
      }
    },
    {
      "actor_id": 60719,
      "model": "movies.actor",
      "fields": {
        "name": "Hiro Kanagawa",
        "profile_path": "https://image.tmdb.org/t/p/original/dyWOPJmZTfy3r3R5eDY2d7yf8Ze.jpg"
      }
    },
    {
      "actor_id": 1267375,
      "model": "movies.actor",
      "fields": {
        "name": "Anna Akana",
        "profile_path": "https://image.tmdb.org/t/p/original/taJmE5h3inYhvrLXO7Dq9IMGhEp.jpg"
      }
    },
    {
      "actor_id": 18702,
      "model": "movies.actor",
      "fields": {
        "name": "Mark Dacascos",
        "profile_path": "https://image.tmdb.org/t/p/original/trOACuJz1KzhB51qe6asaxRuxrh.jpg"
      }
    },
    {
      "actor_id": 2252174,
      "model": "movies.actor",
      "fields": {
        "name": "Teresa Ting",
        "profile_path": "https://image.tmdb.org/t/p/original/saHbkcRxQpjlEhYJFGcFV8rfz2F.jpg"
      }
    },
    {
      "actor_id": 61632,
      "model": "movies.actor",
      "fields": {
        "name": "Dustin Nguyen",
        "profile_path": "https://image.tmdb.org/t/p/original/ejgR5tSZYZ9zC5jKQhG6vtHunvT.jpg"
      }
    },
    {
      "actor_id": 101626,
      "model": "movies.actor",
      "fields": {
        "name": "Dan Southworth",
        "profile_path": "https://image.tmdb.org/t/p/original/2DKM8LkytmWkiQjhq2QGO8n2P5H.jpg"
      }
    },
    {
      "actor_id": 1018984,
      "model": "movies.actor",
      "fields": {
        "name": "Sofia Essaïdi",
        "profile_path": "https://image.tmdb.org/t/p/original/6OSQeJhTJ8nWG0VYtk876OIql0P.jpg"
      }
    },
    {
      "actor_id": 20671,
      "model": "movies.actor",
      "fields": {
        "name": "Assaad Bouab",
        "profile_path": "https://image.tmdb.org/t/p/original/zIqK5a0H3e6z2vFhRDdWQCMQIRT.jpg"
      }
    },
    {
      "actor_id": 110424,
      "model": "movies.actor",
      "fields": {
        "name": "Alberto Ammann",
        "profile_path": "https://image.tmdb.org/t/p/original/8jhuoxRvOTJFHmYh4kmCAZ8Mggj.jpg"
      }
    },
    {
      "actor_id": 26282,
      "model": "movies.actor",
      "fields": {
        "name": "Nicolas Cazalé",
        "profile_path": "https://image.tmdb.org/t/p/original/a1NyEPcJb5BR5l7tHutLP68Jn5D.jpg"
      }
    },
    {
      "actor_id": 1003260,
      "model": "movies.actor",
      "fields": {
        "name": "Nassim Lyes",
        "profile_path": "https://image.tmdb.org/t/p/original/hpj7xUY3Ui8qPYk8Aaui02JsVTm.jpg"
      }
    },
    {
      "actor_id": 49265,
      "model": "movies.actor",
      "fields": {
        "name": "Lindsay Lohan",
        "profile_path": "https://image.tmdb.org/t/p/original/y59roEK1QZqoWhWPlzgWVDmJarq.jpg"
      }
    },
    {
      "actor_id": 232501,
      "model": "movies.actor",
      "fields": {
        "name": "Chord Overstreet",
        "profile_path": "https://image.tmdb.org/t/p/original/drWXFTF9f8h9DRLRtKENCrJKGk1.jpg"
      }
    },
    {
      "actor_id": 1622199,
      "model": "movies.actor",
      "fields": {
        "name": "George Young",
        "profile_path": "https://image.tmdb.org/t/p/original/dDTtlhWEnqIvBoOljmX2Hoi8IO4.jpg"
      }
    },
    {
      "actor_id": 138887,
      "model": "movies.actor",
      "fields": {
        "name": "Jack Wagner",
        "profile_path": "https://image.tmdb.org/t/p/original/zRoZShStnWymvcm7bQDr35qdck6.jpg"
      }
    },
    {
      "actor_id": 1978944,
      "model": "movies.actor",
      "fields": {
        "name": "Olivia Perez",
        "profile_path": "https://image.tmdb.org/t/p/original/oCHMfy0wWd9xuOgn6RYgT4zjCUM.jpg"
      }
    }]